intake_dremio/__init__.py
intake_dremio/_version.py
intake_dremio/dremio_cat.py
intake_dremio/intake_dremio.py
intake_dremio/static/style.css
intake_dremio/tests/__init__.py
intake_dremio/tests/test_intake_dremio.py
intake_dremio-0.2.5.dist-info/LICENSE
intake_dremio-0.2.5.dist-info/METADATA
intake_dremio-0.2.5.dist-info/WHEEL
intake_dremio-0.2.5.dist-info/entry_points.txt
intake_dremio-0.2.5.dist-info/top_level.txt
intake_dremio-0.2.5.dist-info/RECORD
