Metadata-Version: 2.1
Name: intake-dremio
Version: 0.2.5
Summary: Dremio plugin for Intake
Home-page: https://github.com/philippjfr/intake-dremio
Maintainer: Philipp Rudiger
Maintainer-email: prudiger@anaconda.com
License: BSD-3
Requires-Python: >=3.6
License-File: LICENSE
Requires-Dist: pandas >=0.25
Requires-Dist: intake <2
Requires-Dist: pyarrow >=4.0
Provides-Extra: tests
Requires-Dist: pytest ; extra == 'tests'
Requires-Dist: codecov ; extra == 'tests'
Requires-Dist: pytest-cov ; extra == 'tests'
Requires-Dist: flake8 ; extra == 'tests'
Requires-Dist: twine ; extra == 'tests'
Requires-Dist: rfc3986 ; extra == 'tests'
Requires-Dist: keyring ; extra == 'tests'
